setup.cfg
setup.py
sac_math/_init_.py
sac_math/main.py
sac_math.egg-info/PKG-INFO
sac_math.egg-info/SOURCES.txt
sac_math.egg-info/dependency_links.txt
sac_math.egg-info/not-zip-safe
sac_math.egg-info/top_level.txt