Metadata-Version: 2.1
Name: sac_math
Version: 1.1
Summary: sample python package
Author-email: sac_erande@yahoo.co.in
